suggest/__init__.py
suggest/suggest.py
tests/__init__.py
tests/test_address.py
tests/test_cache.py
tests/test_formatter.py
tests/testcase.py
geosupport_suggest-0.1.0.dist-info/METADATA
geosupport_suggest-0.1.0.dist-info/WHEEL
geosupport_suggest-0.1.0.dist-info/entry_points.txt
geosupport_suggest-0.1.0.dist-info/top_level.txt
geosupport_suggest-0.1.0.dist-info/RECORD
