Metadata-Version: 2.1
Name: geosupport-suggest
Version: 0.1.0
Summary: Retrieve address suggestions from Geosupport
Home-page: https://github.com/ishiland/geosupport-suggest
Author: Ian Shiland
Author-email: ishiland@gmail.com
License: MIT
Keywords: NYC,geocoder,python-geosupport,geosupport,geosupport-suggest
Classifier: Development Status :: 4 - Beta
Classifier: Operating System :: Microsoft :: Windows
Classifier: Operating System :: POSIX :: Linux
Classifier: Operating System :: MacOS :: MacOS X
Classifier: Programming Language :: Python :: 3.8
Classifier: Programming Language :: Python :: 3.9
Classifier: Programming Language :: Python :: 3.10
Classifier: Programming Language :: Python :: 3.11
Classifier: Programming Language :: Python :: 3.12
Requires-Python: >=3.8
Requires-Dist: python-geosupport >=1.1.0
Requires-Dist: nyc-parser >=0.1.0
Provides-Extra: dev
Requires-Dist: pytest ; extra == 'dev'
Requires-Dist: pytest-cov ; extra == 'dev'
Requires-Dist: black ; extra == 'dev'
Provides-Extra: docs
Requires-Dist: sphinx >=4.0.0 ; extra == 'docs'
Requires-Dist: sphinx-rtd-theme >=1.0.0 ; extra == 'docs'
Provides-Extra: test
Requires-Dist: pytest ; extra == 'test'
Requires-Dist: pytest-cov ; extra == 'test'
